quickmail/__init__.py
quickmail/cli.py
quickmail/commands/__init__.py
quickmail/commands/clear.py
quickmail/commands/init.py
quickmail/commands/send.py
quickmail/commands/template.py
quickmail/utils/__init__.py
quickmail/utils/misc.py
quick_mail-1.0.4.dist-info/LICENSE
quick_mail-1.0.4.dist-info/METADATA
quick_mail-1.0.4.dist-info/WHEEL
quick_mail-1.0.4.dist-info/entry_points.txt
quick_mail-1.0.4.dist-info/top_level.txt
quick_mail-1.0.4.dist-info/RECORD
